servers/__init__.py
servers/__main__.py
servers/capacitor_calculator.py
servers/combined_server.py
servers/gpio_reference.py
servers/resistor_decoder.py
electronics_mcp_servers-1.0.2.dist-info/METADATA
electronics_mcp_servers-1.0.2.dist-info/WHEEL
electronics_mcp_servers-1.0.2.dist-info/entry_points.txt
electronics_mcp_servers-1.0.2.dist-info/licenses/LICENSE
electronics_mcp_servers-1.0.2.dist-info/RECORD
