Metadata-Version: 2.4
Name: electronics-mcp-servers
Version: 1.0.2
Summary: MCP servers for electronics and embedded development: GPIO pin reference, capacitor calculator, and resistor color code decoder
Author: Samuel F.
License: MIT
License-File: LICENSE
Keywords: capacitor,electronics,embedded,fastmcp,gpio,mcp,resistor
Classifier: Development Status :: 5 - Production/Stable
Classifier: Intended Audience :: Developers
Classifier: License :: OSI Approved :: MIT License
Classifier: Programming Language :: Python :: 3
Classifier: Programming Language :: Python :: 3.10
Classifier: Programming Language :: Python :: 3.11
Classifier: Programming Language :: Python :: 3.12
Classifier: Topic :: Scientific/Engineering :: Electronic Design Automation (EDA)
Requires-Python: >=3.10
Requires-Dist: mcp[cli]>=1.1.0
Provides-Extra: dev
Requires-Dist: pytest-asyncio>=0.23.0; extra == 'dev'
Requires-Dist: pytest>=8.0.0; extra == 'dev'
Requires-Dist: ruff>=0.4.0; extra == 'dev'
